__init__.py
excel2txt.py
excel2txt-0.2.1.dist-info/LICENSE
excel2txt-0.2.1.dist-info/METADATA
excel2txt-0.2.1.dist-info/WHEEL
excel2txt-0.2.1.dist-info/entry_points.txt
excel2txt-0.2.1.dist-info/top_level.txt
excel2txt-0.2.1.dist-info/RECORD
