Metadata-Version: 2.1
Name: excel2txt
Version: 0.2.1
Summary: Convert Excel files to delimited text
Home-page: https://github.com/kyclark/excel2txt-py
Author: Ken Youens-Clark
Author-email: kyclark@gmail.com
License: UNKNOWN
Platform: UNKNOWN
Classifier: Programming Language :: Python :: 3
Classifier: License :: OSI Approved :: MIT License
Classifier: Operating System :: OS Independent
